Metadata-Version: 1.0
Name: aicore-tz-watch-scraper
Version: 0.0.2
Summary: Aicore project that allows the user to scrape mens watch data from the gold smiths website
Home-page: https://github.com/CrownedDev56
Author: Tafadzwa Zama
Author-email: UNKNOWN
License: MIT
Platform: UNKNOWN
